{"cameraMode":{"drawMode":0,"name":"Shaded","section":"Shading Mode"},"sceneLighting":true,"audioPlay":false,"sceneViewState":{"showFog":true,"showMaterialUpdate":false,"showSkybox":true,"showFlares":true,"showImageEffects":true,"showParticleSystems":true},"in2DMode":false,"pivot":{"x":139.25631713867188,"y":66.39297485351563,"z":-34.73069763183594},"rotation":{"x":-0.3861559331417084,"y":-0.055947549641132358,"z":0.023461615666747094,"w":-0.9204944968223572},"size":156.9501190185547,"orthographic":false}